setup.py
ladybug/__init__.py
ladybug/graph_utils.py
ladybug/model.py
ladybug.egg-info/PKG-INFO
ladybug.egg-info/SOURCES.txt
ladybug.egg-info/dependency_links.txt
ladybug.egg-info/top_level.txt