Metadata-Version: 1.1
Name: ladybug
Version: 0.0.1
Summary: Handle CSV files using table models and queries.
Home-page: https://github.com/kdani3/ladybug.py
Author: Dániel Kántor
Author-email: kdani3@gmail.com
License: GPLv3+
Download-URL: https://github.com/kdani3/ladybug.py/tarball/master
Keywords: CSV data model table query
Platform: UNKNOWN
Classifier: Development Status :: 4 - Beta
Classifier: Topic :: Utilities
Classifier: Environment :: Console
Classifier: License :: OSI Approved :: GNU General Public License v3 or later (GPLv3+)
